socii/__init__.py
socii/types/__init__.py
socii/types/attr_mapping.py
socii-0.1.dist-info/DESCRIPTION.rst
socii-0.1.dist-info/METADATA
socii-0.1.dist-info/RECORD
socii-0.1.dist-info/WHEEL
socii-0.1.dist-info/metadata.json
socii-0.1.dist-info/top_level.txt
